nitrogen/__init__.py
nitrogen/app.py
nitrogen/webpage.py
nitrogenfw-1.0.7.data/data/lib/python3.10/site-packages/nitrogen/js/socket.io.js
nitrogenfw-1.0.7.data/data/lib/python3.10/site-packages/nitrogen/js/wrapper.js
nitrogenfw-1.0.7.dist-info/LICENSE.txt
nitrogenfw-1.0.7.dist-info/METADATA
nitrogenfw-1.0.7.dist-info/WHEEL
nitrogenfw-1.0.7.dist-info/top_level.txt
nitrogenfw-1.0.7.dist-info/RECORD
