Metadata-Version: 2.1
Name: nitrogenfw
Version: 1.0.7
Summary: A framework to build desktop apps with web technologies
Home-page: https://github.com/ii-Python/nitrogen
Author: iiPython
Author-email: ben@iipython.cf
License: MIT
Platform: UNKNOWN
Classifier: License :: OSI Approved :: MIT License
Classifier: Programming Language :: Python :: 3
Requires-Python: >=3.8, <4
License-File: LICENSE.txt
Requires-Dist: flask
Requires-Dist: jinja2
Requires-Dist: eventlet
Requires-Dist: requests
Requires-Dist: flask-socketio
Requires-Dist: PyQt5
Requires-Dist: PyQtWebEngine
